rd_webhooks/__init__.py
rd_webhooks/application.py
rd_webhooks/constants.py
rd_webhooks/exceptions.py
rd_webhooks/api/echo.py
rd_webhooks/api/echo.yml
rd_webhooks/api/metrics.py
rd_webhooks/api/metrics.yml
rd_webhooks/api/openapi.yml
rd_webhooks/api/status.py
rd_webhooks/api/status.yml
rd_webhooks/api/x-gitlab.yml
rd_webhooks/api/x-responses.yml
rd_webhooks/api/badges/static.py
rd_webhooks/api/badges/static.yml
rd_webhooks/api/redirects/gitlab/pages.py
rd_webhooks/api/redirects/gitlab/pages.yml
rd_webhooks/clients/__init__.py
rd_webhooks/clients/gitlab.py
rd_webhooks/models/__init__.py
rd_webhooks/models/badges.py
rd_webhooks/utils/__init__.py
rd_webhooks/utils/enums.py
rd_webhooks-0.0.1.dist-info/LICENSE
rd_webhooks-0.0.1.dist-info/METADATA
rd_webhooks-0.0.1.dist-info/WHEEL
rd_webhooks-0.0.1.dist-info/entry_points.txt
rd_webhooks-0.0.1.dist-info/top_level.txt
rd_webhooks-0.0.1.dist-info/RECORD
